py_epc_qr/__init__.py
py_epc_qr/__main__.py
py_epc_qr/checks.py
py_epc_qr/cli.py
py_epc_qr/constants.py
py_epc_qr/transaction.py
py_epc_qr-0.1.3.dist-info/entry_points.txt
py_epc_qr-0.1.3.dist-info/WHEEL
py_epc_qr-0.1.3.dist-info/METADATA
py_epc_qr-0.1.3.dist-info/RECORD
