Metadata-Version: 2.1
Name: py-epc-qr
Version: 0.1.3
Summary: Generate EPC-compatible QR codes for wire transfers
Home-page: https://github.com/timueh/py-epc-qr
License: MIT
Author: timueh
Author-email: t.muehlpfordt@mailbox.org
Requires-Python: >=3.9,<4.0
Classifier: License :: OSI Approved :: MIT License
Classifier: Programming Language :: Python :: 3
Classifier: Programming Language :: Python :: 3.10
Classifier: Programming Language :: Python :: 3.9
Requires-Dist: Pillow (>=9.1.0,<10.0.0)
Requires-Dist: PyYAML (>=6.0,<7.0)
Requires-Dist: qrcode (>=7.3.1,<8.0.0)
Requires-Dist: typer (>=0.4.1,<0.5.0)
Project-URL: Documentation, https://github.com/timueh/py-epc-qr
Project-URL: Repository, https://github.com/timueh/py-epc-qr
